moethread/__init__.py
moethread/main.py
moethread/version.py
moethread-1.4.2.dist-info/LICENSE
moethread-1.4.2.dist-info/METADATA
moethread-1.4.2.dist-info/WHEEL
moethread-1.4.2.dist-info/top_level.txt
moethread-1.4.2.dist-info/RECORD
