Metadata-Version: 2.1
Name: moethread
Version: 1.4.2
Summary: Python wrapper for ThreadPoolExecutor to easily multithread resource bound tasks
Home-page: https://github.com/mhamdan91/moethread
Author: mhamdan91 (Hamdan, Muhammad)
Author-email: <mhamdan.dev@gmail.com>
Keywords: python,multithreading,wrappers,decorator,pool,multitasking,easy multithreading,thread,parallel,concurrent
Classifier: Development Status :: 5 - Production/Stable
Classifier: Intended Audience :: Developers
Classifier: Programming Language :: Python :: 3
Classifier: Operating System :: Unix
Classifier: Operating System :: MacOS :: MacOS X
Classifier: Operating System :: Microsoft :: Windows
Classifier: License :: OSI Approved :: MIT License
License-File: LICENSE
Requires-Dist: moecolor
